{
  "aliases": [],
  "canonical_output_form": "--oom-kill-disable",
  "compare_profile": {
    "fields": [
      "HostConfig.OomKillDisable"
    ],
    "profile": "inspect-projection"
  },
  "detection_profile": {
    "fields": [
      "HostConfig.OomKillDisable"
    ],
    "profile": "inspect-fields"
  },
  "id": "oom-kill-disable",
  "inspect_fields": [
    "HostConfig.OomKillDisable"
  ],
  "manifest_flags": [
    "--oom-kill-disable"
  ],
  "observability": "observable",
  "path_coverage": {
    "container_name": "runner_blocked",
    "stdin": "runner_blocked"
  },
  "priority": "P1",
  "render_profile": {
    "command_family": "both",
    "flag": "--oom-kill-disable",
    "profile": "canonical-docker-flag",
    "value_type": null
  },
  "scope": {
    "classification": "blocked_by_runner",
    "reason": "needs_kernel_oom_kill_disable_support"
  },
  "warning_behavior": {
    "warn_when_detected_unsupported": false
  }
}
